[
  {
    "id": 1,
    "question": "Which part of speech performs the action or state of being in a sentence?",
    "options": [
      "Noun",
      "Verb",
      "Adjective",
      "Adverb"
    ],
    "answer": "Verb",
    "explanation": "A verb expresses a physical action (e.g., 'run'), a mental action (e.g., 'think'), or a state of being (e.g., 'is'). Nouns name things, while adjectives and adverbs modify them.",
    "difficulty": "Beginner"
  },
  {
    "id": 2,
    "question": "Identify the subject in the following sentence: 'The quick brown fox jumps over the lazy dog.'",
    "options": [
      "The quick brown fox",
      "Jumps",
      "The lazy dog",
      "Over"
    ],
    "answer": "The quick brown fox",
    "explanation": "The subject is the person, place, thing, or idea that is doing or being something. Here, the fox is the one performing the action of jumping.",
    "difficulty": "Beginner"
  },
  {
    "id": 3,
    "question": "Which sentence demonstrates the correct use of the present continuous tense?",
    "options": [
      "She eats breakfast right now.",
      "She is eating breakfast right now.",
      "She eating breakfast right now.",
      "She has eaten breakfast right now."
    ],
    "answer": "She is eating breakfast right now.",
    "explanation": "The present continuous tense is formed using 'to be' (am/is/are) + the verb-ing. It describes an action happening at the current moment.",
    "difficulty": "Beginner"
  },
  {
    "id": 4,
    "question": "Which pronoun correctly completes the sentence: 'Please give the package to ___'?",
    "options": [
      "he",
      "they",
      "we",
      "me"
    ],
    "answer": "me",
    "explanation": "'Me' is an object pronoun used when the pronoun receives the action. 'He', 'she', and 'we' are subject pronouns used to perform the action.",
    "difficulty": "Beginner"
  },
  {
    "id": 5,
    "question": "Which word in the following sentence is an adjective: 'The red car stopped quickly.'?",
    "options": [
      "The",
      "Red",
      "Car",
      "Stopped"
    ],
    "answer": "Red",
    "explanation": "An adjective modifies or describes a noun. 'Red' describes the noun 'car', whereas 'stopped' is a verb and 'quickly' is an adverb.",
    "difficulty": "Beginner"
  },
  {
    "id": 6,
    "question": "Select the correct sentence structure.",
    "options": [
      "Subject + Verb + Object",
      "Object + Verb + Subject",
      "Verb + Subject + Object",
      "Adjective + Noun + Verb"
    ],
    "answer": "Subject + Verb + Object",
    "explanation": "Standard English syntax typically follows the Subject-Verb-Object (SVO) order (e.g., 'The dog [S] chased [V] the ball [O]').",
    "difficulty": "Beginner"
  },
  {
    "id": 7,
    "question": "Which word is a countable noun?",
    "options": [
      "Water",
      "Information",
      "Apple",
      "Rice"
    ],
    "answer": "Apple",
    "explanation": "Countable nouns can be counted as individual units (e.g., one apple, two apples). 'Water', 'information', and 'rice' are uncountable mass nouns.",
    "difficulty": "Beginner"
  },
  {
    "id": 8,
    "question": "Complete the sentence with the correct article: 'I saw ___ owl in the tree.'",
    "options": [
      "a",
      "an",
      "the",
      "no article"
    ],
    "answer": "an",
    "explanation": "'An' is used before words starting with a vowel sound. 'Owl' begins with a vowel sound (/aʊ/), so 'an' is the correct indefinite article.",
    "difficulty": "Beginner"
  },
  {
    "id": 9,
    "question": "What is the past tense form of the verb 'to walk'?",
    "options": [
      "Walked",
      "Walking",
      "Walks",
      "Has walked"
    ],
    "answer": "Walked",
    "explanation": "For regular verbs, the past tense is formed by adding '-ed' to the base form. 'Walks' is present, 'walking' is a participle, and 'has walked' is present perfect.",
    "difficulty": "Beginner"
  },
  {
    "id": 10,
    "question": "Which sentence uses the preposition of time correctly?",
    "options": [
      "I will see you at 5 PM.",
      "I will see you in 5 PM.",
      "I will see you on 5 PM.",
      "I will see you with 5 PM."
    ],
    "answer": "I will see you at 5 PM.",
    "explanation": "'At' is used for precise times. 'In' is used for months, years, or parts of the day (in the morning), and 'on' is for specific days.",
    "difficulty": "Beginner"
  },
  {
    "id": 11,
    "question": "Which sentence demonstrates correct subject-verb agreement?",
    "options": [
      "The list of items are on the desk.",
      "The list of items is on the desk.",
      "The list of items were on the desk.",
      "The list of items have been on the desk."
    ],
    "answer": "The list of items is on the desk.",
    "explanation": "The subject is 'list' (singular), not 'items' (plural). Therefore, the singular verb 'is' must be used.",
    "difficulty": "Beginner"
  },
  {
    "id": 12,
    "question": "Choose the correct word to complete the sentence: 'There are ___ apples in the basket.'",
    "options": [
      "Much",
      "Any",
      "Many",
      "A little"
    ],
    "answer": "Many",
    "explanation": "'Many' is used with countable nouns (apples). 'Much' and 'a little' are used for uncountable nouns, while 'any' is typically used in questions or negatives.",
    "difficulty": "Beginner"
  },
  {
    "id": 13,
    "question": "Identify the compound sentence structure.",
    "options": [
      "Because it rained, we stayed inside.",
      "It rained, but we went out anyway.",
      "It rained.",
      "Although it rained, we went out."
    ],
    "answer": "It rained, but we went out anyway.",
    "explanation": "A compound sentence connects two independent clauses with a coordinating conjunction (like 'but'). The other options are complex sentences.",
    "difficulty": "Beginner"
  },
  {
    "id": 14,
    "question": "Which word modifies the verb 'ran' in the sentence: 'He ran quickly to the store.'?",
    "options": [
      "He",
      "Ran",
      "Quickly",
      "Store"
    ],
    "answer": "Quickly",
    "explanation": "Adverbs modify verbs, adjectives, or other adverbs, often ending in '-ly'. 'Quickly' describes *how* he ran.",
    "difficulty": "Beginner"
  },
  {
    "id": 15,
    "question": "What is the correct plural form of 'child'?",
    "options": [
      "Childs",
      "Children",
      "Childes",
      "Child's"
    ],
    "answer": "Children",
    "explanation": "'Child' is an irregular noun. It does not follow the standard '-s' rule and changes to 'Children' in the plural form.",
    "difficulty": "Beginner"
  },
  {
    "id": 16,
    "question": "Which modal verb expresses ability in the past?",
    "options": [
      "Can",
      "Must",
      "Could",
      "Should"
    ],
    "answer": "Could",
    "explanation": "'Could' is the past tense form of 'can' and expresses the ability to do something in the past.",
    "difficulty": "Beginner"
  },
  {
    "id": 17,
    "question": "Select the correct sentence using the possessive form.",
    "options": [
      "The dog's bone is buried.",
      "The dogs bone is buried.",
      "The dogs' bone is buried.",
      "The doges bone is buried."
    ],
    "answer": "The dog's bone is buried.",
    "explanation": "To show possession for a singular noun, add an apostrophe and an 's' (dog's). 'Dogs'' would imply multiple dogs.",
    "difficulty": "Beginner"
  },
  {
    "id": 18,
    "question": "Which is an example of a proper noun?",
    "options": [
      "City",
      "London",
      "River",
      "Mountain"
    ],
    "answer": "London",
    "explanation": "A proper noun is the specific name of a person, place, or organization and is always capitalized. 'City', 'river', and 'mountain' are common nouns.",
    "difficulty": "Beginner"
  },
  {
    "id": 19,
    "question": "What is the function of the word 'and' in the sentence: 'Bread and butter are delicious.'?",
    "options": [
      "Preposition",
      "Conjunction",
      "Interjection",
      "Pronoun"
    ],
    "answer": "Conjunction",
    "explanation": "'And' is a coordinating conjunction used to connect words, phrases, or clauses.",
    "difficulty": "Beginner"
  },
  {
    "id": 20,
    "question": "Which sentence is in the passive voice?",
    "options": [
      "The chef cooked the meal.",
      "The meal was cooked by the chef.",
      "The chef is cooking the meal.",
      "The meal tastes good."
    ],
    "answer": "The meal was cooked by the chef.",
    "explanation": "Passive voice emphasizes the recipient of the action (the meal) rather than the doer, using 'to be' + past participle ('was cooked').",
    "difficulty": "Beginner"
  },
  {
    "id": 21,
    "question": "Choose the correct comparative form of the adjective 'good'.",
    "options": [
      "Gooder",
      "More good",
      "Better",
      "Goodest"
    ],
    "answer": "Better",
    "explanation": "'Good' is an irregular adjective. Its comparative form is 'better', not 'gooder' or 'more good'.",
    "difficulty": "Beginner"
  },
  {
    "id": 22,
    "question": "Which word is a synonym for 'happy'?",
    "options": [
      "Sad",
      "Joyful",
      "Angry",
      "Tired"
    ],
    "answer": "Joyful",
    "explanation": "A synonym is a word with the same or nearly the same meaning. 'Joyful' means feeling, expressing, or causing great pleasure and happiness.",
    "difficulty": "Beginner"
  },
  {
    "id": 23,
    "question": "Complete the sentence with the correct pronoun: 'That book belongs to ___.'",
    "options": [
      "his",
      "he",
      "him",
      "their"
    ],
    "answer": "his",
    "explanation": "The sentence requires a possessive pronoun to indicate ownership. 'His' functions as a possessive pronoun here.",
    "difficulty": "Beginner"
  },
  {
    "id": 24,
    "question": "Which punctuation mark ends an imperative sentence?",
    "options": [
      "Question mark",
      "Period or Exclamation mark",
      "Comma",
      "Colon"
    ],
    "answer": "Period or Exclamation mark",
    "explanation": "Imperative sentences give commands or requests. They typically end with a period, but an exclamation mark is used for strong emotion.",
    "difficulty": "Beginner"
  },
  {
    "id": 25,
    "question": "Identify the direct object in the sentence: 'She kicked the ball.'",
    "options": [
      "She",
      "Kicked",
      "Ball",
      "The"
    ],
    "answer": "Ball",
    "explanation": "The direct object receives the action of the verb. Here, 'the ball' is what received the kick.",
    "difficulty": "Beginner"
  },
  {
    "id": 26,
    "question": "What is the superlative form of 'dangerous'?",
    "options": [
      "Dangerouser",
      "More dangerous",
      "Most dangerous",
      "Dangerousmost"
    ],
    "answer": "Most dangerous",
    "explanation": "For longer adjectives (usually three syllables or more), the superlative is formed by adding 'most' before the adjective.",
    "difficulty": "Beginner"
  },
  {
    "id": 27,
    "question": "Which sentence correctly uses 'few' with a countable noun?",
    "options": [
      "I have few money.",
      "There are few people here.",
      "She has few time.",
      "We drank few water."
    ],
    "answer": "There are few people here.",
    "explanation": "'Few' is used with countable nouns (people). 'Money', 'time', and 'water' are uncountable and require 'little'.",
    "difficulty": "Beginner"
  },
  {
    "id": 28,
    "question": "Which relative pronoun is used to refer to things?",
    "options": [
      "Who",
      "Whom",
      "Which",
      "Whose"
    ],
    "answer": "Which",
    "explanation": "'Which' is the relative pronoun used for animals and things. 'Who' and 'whom' are used for people, while 'whose' indicates possession.",
    "difficulty": "Beginner"
  },
  {
    "id": 29,
    "question": "Identify the linking verb in the sentence: 'She seems tired.'",
    "options": [
      "She",
      "Seems",
      "Tired",
      "She seems"
    ],
    "answer": "Seems",
    "explanation": "A linking verb connects the subject ('She') to a subject complement ('tired') rather than showing action. 'Seems' acts as this link.",
    "difficulty": "Beginner"
  },
  {
    "id": 30,
    "question": "Select the correct word to complete the idiom: 'It is raining ___ and dogs.'",
    "options": [
      "Cats",
      "Frogs",
      "Cows",
      "Birds"
    ],
    "answer": "Cats",
    "explanation": "The standard English idiom for very heavy rain is 'It's raining cats and dogs.'",
    "difficulty": "Beginner"
  },
  {
    "id": 31,
    "question": "Which prefix creates a word that means the opposite of 'agree'?",
    "options": [
      "Re-",
      "Pre-",
      "Dis-",
      "Un-"
    ],
    "answer": "Dis-",
    "explanation": "'Disagree' is the correct antonym. 'Un-' is also a negative prefix (unhappy), but 'disagree' is the standard vocabulary pairing.",
    "difficulty": "Beginner"
  },
  {
    "id": 32,
    "question": "Choose the sentence that uses 'its' correctly.",
    "options": [
      "The dog wagged it's tail.",
      "The dog wagged its tail.",
      "Its tail wagging the dog.",
      "The dog wagged its' tail."
    ],
    "answer": "The dog wagged its tail.",
    "explanation": "'Its' is the possessive form of 'it'. 'It's' is a contraction of 'it is', which would be incorrect here.",
    "difficulty": "Beginner"
  },
  {
    "id": 33,
    "question": "Which verb mood is used to express a command?",
    "options": [
      "Indicative",
      "Subjunctive",
      "Imperative",
      "Conditional"
    ],
    "answer": "Imperative",
    "explanation": "The imperative mood is used for commands and instructions (e.g., 'Close the door'). Indicative states facts, subjunctive wishes/hypotheticals.",
    "difficulty": "Beginner"
  },
  {
    "id": 34,
    "question": "Which conjunction pair is used to join two contrasting ideas?",
    "options": [
      "Both... and",
      "Either... or",
      "Neither... nor",
      "Not only... but also"
    ],
    "answer": "Either... or",
    "explanation": "'Either... or' presents a choice between distinct alternatives. While 'but' contrasts, 'either... or' is the specific correlative conjunction for choices.",
    "difficulty": "Beginner"
  },
  {
    "id": 35,
    "question": "Identify the gerund in the sentence: 'Swimming is fun.'",
    "options": [
      "Swimming",
      "Is",
      "Fun",
      "Is fun"
    ],
    "answer": "Swimming",
    "explanation": "A gerund is a verb ending in '-ing' that functions as a noun. Here, 'Swimming' acts as the subject of the sentence.",
    "difficulty": "Beginner"
  },
  {
    "id": 36,
    "question": "Which tense formation correctly follows the auxiliary verb 'had' in the Past Perfect tense?",
    "options": [
      "The base form of the main verb",
      "The present participle (-ing form)",
      "The past participle (-ed or irregular form)",
      "The infinitive form of the main verb"
    ],
    "answer": "The past participle (-ed or irregular form)",
    "explanation": "The Past Perfect tense is formed using 'had' followed by the past participle of the main verb (e.g., 'had finished'). This structure establishes that the action occurred before another past action.",
    "difficulty": "Intermediate"
  },
  {
    "id": 37,
    "question": "In the context of future time clauses, which rule governs the verb tense following conjunctions like 'when', 'after', and 'before'?",
    "options": [
      "The verb must be in the future tense (will + verb)",
      "The verb must be in the present tense to represent future meaning",
      "The verb must be in the conditional tense (would + verb)",
      "The verb must be in the past perfect tense"
    ],
    "answer": "The verb must be in the present tense to represent future meaning",
    "explanation": "English grammar rules dictate that time clauses referring to the future cannot use the future tense. Instead, the present tense (simple or continuous) is used to express future time within these dependent clauses.",
    "difficulty": "Intermediate"
  },
  {
    "id": 38,
    "question": "What distinguishes the grammatical usage of 'less' versus 'fewer' when modifying nouns?",
    "options": [
      "'Less' is used for countable nouns; 'fewer' is used for uncountable nouns",
      "'Fewer' is used for countable nouns; 'less' is used for uncountable nouns",
      "'Less' is used for plural nouns; 'fewer' is used for singular nouns",
      "They are interchangeable in all contexts"
    ],
    "answer": "'Fewer' is used for countable nouns; 'less' is used for uncountable nouns",
    "explanation": "'Fewer' modifies nouns that can be counted (e.g., 'fewer dollars'), while 'less' modifies nouns that represent a bulk amount or concept (e.g., 'less money'). This distinction maintains precision in quantity description.",
    "difficulty": "Intermediate"
  },
  {
    "id": 39,
    "question": "Which sentence structure demonstrates a causative construction using 'have'?",
    "options": [
      "I had my car repair by the mechanic",
      "I had my car repaired by the mechanic",
      "I had my car repairing by the mechanic",
      "I had my car to repair by the mechanic"
    ],
    "answer": "I had my car repaired by the mechanic",
    "explanation": "The causative 'have' is formed with 'have' + object + past participle. This structure indicates that the subject caused the action to be done by someone else, rather than doing it themselves.",
    "difficulty": "Intermediate"
  },
  {
    "id": 40,
    "question": "When using the verb 'make' to express causation, which verb form follows the direct object?",
    "options": [
      "The to-infinitive (to + base verb)",
      "The gerund (-ing form)",
      "The bare infinitive (base verb without 'to')",
      "The present participle"
    ],
    "answer": "The bare infinitive (base verb without 'to')",
    "explanation": "In active causative structures with 'make', the pattern is 'make' + object + bare infinitive (e.g., 'She made him leave'). This distinguishes it from other causatives like 'see' or 'hear' which can take participles.",
    "difficulty": "Intermediate"
  },
  {
    "id": 41,
    "question": "What determines whether a collective noun like 'committee' takes a singular or plural verb?",
    "options": [
      "Whether the noun is abstract or concrete",
      "Whether the collective noun is acting as a single unit or as separate individuals",
      "The position of the noun in the sentence",
      "The tense of the sentence"
    ],
    "answer": "Whether the collective noun is acting as a single unit or as separate individuals",
    "explanation": "Subject-verb agreement for collective nouns depends on notional concord. If the group acts in unison, the verb is singular; if members act individually, the verb is plural (more common in British English).",
    "difficulty": "Intermediate"
  },
  {
    "id": 42,
    "question": "Which grammatical error defines a 'dangling participle'?",
    "options": [
      "A participle that modifies the wrong noun in the sentence",
      "A participle at the start of a sentence that does not logically modify the subject of the main clause",
      "A participle used in the past tense instead of the present tense",
      "A participle missing an auxiliary verb"
    ],
    "answer": "A participle at the start of a sentence that does not logically modify the subject of the main clause",
    "explanation": "A dangling participle occurs when the introductory phrase is intended to modify a noun that is not the subject. This results in illogical statements (e.g., 'Walking to the store, the rain fell').",
    "difficulty": "Intermediate"
  },
  {
    "id": 43,
    "question": "In the context of the Past Perfect tense, how is 'non-occurrence' emphasized when used with 'before'?",
    "options": [
      "By using the past continuous tense",
      "By using the Past Perfect tense (had + past participle) to show the event did not finish",
      "By using the auxiliary verb 'would' before the main verb",
      "By placing the adverb 'never' immediately after 'before'"
    ],
    "answer": "By using the Past Perfect tense (had + past participle) to show the event did not finish",
    "explanation": "Using Past Perfect after 'before' (e.g., 'before it had completed') stresses that the event was cut off or never concluded. The Past Simple suggests completion but is less emphatic about the non-occurrence aspect.",
    "difficulty": "Intermediate"
  },
  {
    "id": 44,
    "question": "Which modal verb is typically used to express a hypothetical situation or a 'wish' regarding the present or future?",
    "options": [
      "Will",
      "Shall",
      "Would",
      "Can"
    ],
    "answer": "Would",
    "explanation": "'Would' is the past form of 'will' and is used to express the subjunctive mood, indicating hypothetical or imaginary situations (e.g., 'I wish I would go'). 'Will' indicates definite future intent.",
    "difficulty": "Intermediate"
  },
  {
    "id": 45,
    "question": "What is the function of the Present Perfect Continuous tense compared to the Present Perfect Simple?",
    "options": [
      "It emphasizes the result of a completed action",
      "It emphasizes the duration or activity of an action continuing up to the present",
      "It describes a scheduled future event",
      "It narrates a sequence of past events"
    ],
    "answer": "It emphasizes the duration or activity of an action continuing up to the present",
    "explanation": "While Present Perfect Simple focuses on the completion ('I have painted the room'), Present Perfect Continuous focuses on the activity's duration ('I have been painting the room'). The focus is on the process, not necessarily the result.",
    "difficulty": "Intermediate"
  },
  {
    "id": 46,
    "question": "Which sentence correctly applies the rule regarding pronouns following a preposition?",
    "options": [
      "Between you and I, the project is failing",
      "Between you and me, the project is failing",
      "Between you and myself, the project is failing",
      "Between you and we, the project is failing"
    ],
    "answer": "Between you and me, the project is failing",
    "explanation": "Prepositions must be followed by object pronouns (me, him, her, us, them). 'I' is a subject pronoun, and 'myself' is a reflexive pronoun inappropriate for this compound object structure.",
    "difficulty": "Intermediate"
  },
  {
    "id": 47,
    "question": "In conditional sentences (Type 2), what tense is used in the 'if-clause' to describe a present or future hypothetical situation?",
    "options": [
      "The Past Simple tense",
      "The Present Simple tense",
      "The Past Perfect tense",
      "The Future Simple tense"
    ],
    "answer": "The Past Simple tense",
    "explanation": "Second Conditionals use the Past Simple in the if-clause to indicate distance from reality (unreal present), while 'would' is used in the main clause (e.g., 'If I knew... I would tell you').",
    "difficulty": "Intermediate"
  },
  {
    "id": 48,
    "question": "Which relative pronoun is correctly used for a non-defining relative clause that refers to a thing?",
    "options": [
      "Which",
      "That",
      "What",
      "Whom"
    ],
    "answer": "Which",
    "explanation": "In non-defining clauses (commas), 'which' refers to things, while 'who' refers to people. 'That' is generally not used in non-defining clauses in formal English.",
    "difficulty": "Intermediate"
  },
  {
    "id": 49,
    "question": "What is the correct auxiliary verb order in a question tag following the statement 'She hardly speaks,'?",
    "options": [
      "doesn't she",
      "does she",
      "isn't she",
      "has she"
    ],
    "answer": "does she",
    "explanation": "Question tags use the opposite polarity of the main verb. 'Hardly' is a negative word, so the tag must be positive ('does she'), despite the statement not containing 'not'.",
    "difficulty": "Intermediate"
  },
  {
    "id": 50,
    "question": "Which form of the verb 'to be' acts as the subject in a cleft sentence such as '______ the manager who resigned'?",
    "options": [
      "It was",
      "There is",
      "What was",
      "That is"
    ],
    "answer": "It was",
    "explanation": "The 'It-cleft' structure follows the pattern: It + form of be + focus + relative clause. This structure is used to emphasize a specific noun or phrase.",
    "difficulty": "Intermediate"
  },
  {
    "id": 51,
    "question": "When changing direct speech 'I must leave,' to reported speech, how does the modal verb 'must' typically change?",
    "options": [
      "It changes to 'can'",
      "It changes to 'had to'",
      "It remains 'must'",
      "It changes to 'should'"
    ],
    "answer": "It changes to 'had to'",
    "explanation": "When 'must' expresses obligation in the past during reported speech backshift, it usually changes to 'had to'. 'Must' can remain 'must' if it implies a future deduction or permanent rule, but 'had to' is the standard obligation shift.",
    "difficulty": "Intermediate"
  },
  {
    "id": 52,
    "question": "Which sentence demonstrates correct subject-verb agreement with a singular indefinite pronoun?",
    "options": [
      "Each of the students have finished the exam",
      "Everyone in the group are agreeing with the decision",
      "Neither of the options are correct",
      "Each of the students has finished the exam"
    ],
    "answer": "Each of the students has finished the exam",
    "explanation": "Indefinite pronouns like 'each', 'everyone', and 'everybody' are grammatically singular and require singular verbs ('has'), even if they are logically plural (the students).",
    "difficulty": "Intermediate"
  },
  {
    "id": 53,
    "question": "What is the correct use of the subjunctive mood in a formal recommendation?",
    "options": [
      "I suggest that he studies harder",
      "I suggest that he study harder",
      "I suggest that he studied harder",
      "I suggest that he is studying harder"
    ],
    "answer": "I suggest that he study harder",
    "explanation": "The mandative subjunctive uses the base form of the verb (not the -s form) in a 'that' clause following verbs of recommendation or demand. It emphasizes the urgency or necessity of the action.",
    "difficulty": "Intermediate"
  },
  {
    "id": 54,
    "question": "Which phrase acts as an adverbial connector indicating a contrast between two ideas?",
    "options": [
      "Furthermore",
      "Consequently",
      "On the other hand",
      "In addition"
    ],
    "answer": "On the other hand",
    "explanation": "'On the other hand' is a transition signal used to introduce a contrasting point of view. 'Furthermore' and 'In addition' indicate addition, while 'Consequently' indicates cause and effect.",
    "difficulty": "Intermediate"
  },
  {
    "id": 55,
    "question": "In the sentence 'I look forward to seeing you,' why is the '-ing' form required?",
    "options": [
      "It follows the modal verb 'will'",
      "It follows the preposition 'to'",
      "It is a gerund acting as the direct object",
      "It indicates a continuous action"
    ],
    "answer": "It follows the preposition 'to'",
    "explanation": "In the phrasal verb 'look forward to,' the word 'to' functions as a preposition, not an infinitive marker. Verbs following prepositions must take the gerund (-ing) form.",
    "difficulty": "Intermediate"
  },
  {
    "id": 56,
    "question": "Which conditional structure is used to express a regret about a past event that cannot be changed?",
    "options": [
      "Type 1 Conditional",
      "Type 2 Conditional",
      "Type 3 Conditional",
      "Zero Conditional"
    ],
    "answer": "Type 3 Conditional",
    "explanation": "The Third Conditional describes a hypothetical past situation and its result. It uses 'If + Past Perfect, ... would have + past participle' to express past regrets or alternative pasts.",
    "difficulty": "Intermediate"
  },
  {
    "id": 57,
    "question": "What is the correct term for the grammatical voice where the subject receives the action of the verb?",
    "options": [
      "Active voice",
      "Passive voice",
      "Middle voice",
      "Reciprocal voice"
    ],
    "answer": "Passive voice",
    "explanation": "In passive voice, the grammatical subject is the recipient of the action (e.g., 'The ball was thrown by John'). This contrasts with active voice, where the subject performs the action.",
    "difficulty": "Intermediate"
  },
  {
    "id": 58,
    "question": "Which verb form is used after 'would rather' to express a preference for someone else's action?",
    "options": [
      "The infinitive without to",
      "The past tense",
      "The past participle",
      "The gerund"
    ],
    "answer": "The past tense",
    "explanation": "When 'would rather' is followed by an object and a clause describing another person's action, the past tense is used (e.g., 'I would rather you went').",
    "difficulty": "Intermediate"
  },
  {
    "id": 59,
    "question": "Which word is a demonstrative adjective in the sentence 'Give me that book'?",
    "options": [
      "Give",
      "Me",
      "That",
      "Book"
    ],
    "answer": "That",
    "explanation": "'That' is a demonstrative adjective modifying the noun 'book', specifying which book is being referred to. Demonstratives indicate specific items relative to space or time.",
    "difficulty": "Intermediate"
  },
  {
    "id": 60,
    "question": "In the sentence 'The movie, which was released yesterday, is boring,' what is the grammatical function of the bolded phrase?",
    "options": [
      "It is a defining relative clause",
      "It is a non-defining relative clause",
      "It is an adverbial clause of time",
      "It is a reduced relative clause"
    ],
    "answer": "It is a non-defining relative clause",
    "explanation": "The clause is set off by commas and adds extra information about 'The movie' without identifying it. If removed, the sentence 'The movie is boring' remains grammatically complete.",
    "difficulty": "Intermediate"
  },
  {
    "id": 61,
    "question": "Which verb form typically follows the causative verb 'get'?",
    "options": [
      "The bare infinitive",
      "The past participle",
      "The to-infinitive",
      "The present participle"
    ],
    "answer": "The past participle",
    "explanation": "The causative structure with 'get' follows the pattern 'get' + object + past participle (e.g., 'I got my car fixed'). This is synonymous with 'have something done' in informal contexts.",
    "difficulty": "Intermediate"
  },
  {
    "id": 62,
    "question": "What is the function of the 'zero article' in English grammar?",
    "options": [
      "To indicate a specific noun previously mentioned",
      "To indicate plural or uncountable nouns in a general sense",
      "To indicate the absence of a verb in a sentence",
      "To replace the definite article 'the' before vowels"
    ],
    "answer": "To indicate plural or uncountable nouns in a general sense",
    "explanation": "The zero article refers to the omission of an article (a/an/the) before plural countable nouns or uncountable nouns when referring to them in a general, non-specific way (e.g., 'I like cats').",
    "difficulty": "Intermediate"
  },
  {
    "id": 63,
    "question": "Which pronoun case is required when comparing two subjects in the sentence 'She is taller than ____'?",
    "options": [
      "Me (objective case)",
      "I (subjective case)",
      "Myself (reflexive case)",
      "Mine (possessive case)"
    ],
    "answer": "I (subjective case)",
    "explanation": "The pronoun follows the conjunction 'than' and functions as the subject of the elliptical clause 'than I am.' Therefore, the subjective case 'I' is technically required in formal grammar.",
    "difficulty": "Intermediate"
  },
  {
    "id": 64,
    "question": "Which sentence illustrates a 'fronted' adverbial for stylistic emphasis?",
    "options": [
      "I quickly ran to the store",
      "To the store I ran quickly",
      "Running to the store was quick",
      "I ran to the store with speed"
    ],
    "answer": "To the store I ran quickly",
    "explanation": "Fronting involves moving a phrase (like the prepositional phrase 'To the store') to the beginning of the sentence to place emphasis on it or improve the flow of information.",
    "difficulty": "Intermediate"
  },
  {
    "id": 65,
    "question": "Which modal verb expresses a logical deduction or conclusion about a past event?",
    "options": [
      "Must have + past participle",
      "Should have + past participle",
      "Can have + past participle",
      "Will have + past participle"
    ],
    "answer": "Must have + past participle",
    "explanation": "'Must have + past participle' expresses strong certainty about a past event based on evidence (e.g., 'The ground is wet; it must have rained'). 'Should have' implies unfulfilled expectation.",
    "difficulty": "Intermediate"
  },
  {
    "id": 66,
    "question": "What is the correct grammatical term for the '-ing' form functioning as a noun?",
    "options": [
      "Participle",
      "Gerund",
      "Infinitive",
      "Auxiliary"
    ],
    "answer": "Gerund",
    "explanation": "While the form looks identical to the present participle, a gerund functions specifically as a noun (e.g., 'Swimming is fun'). Participles function as adjectives or parts of continuous verb tenses.",
    "difficulty": "Intermediate"
  },
  {
    "id": 67,
    "question": "In the sentence 'Whom did you see?', what is the case of the pronoun 'Whom'?",
    "options": [
      "Nominative case",
      "Objective case",
      "Possessive case",
      "Reflexive case"
    ],
    "answer": "Objective case",
    "explanation": "'Whom' is the objective form of 'who', used when the pronoun is the object of a verb or preposition. Here, it is the object of the verb 'see'.",
    "difficulty": "Intermediate"
  },
  {
    "id": 68,
    "question": "Which tense is used to describe an action that was completed before another moment in the past?",
    "options": [
      "Present Perfect",
      "Past Simple",
      "Past Perfect",
      "Past Continuous"
    ],
    "answer": "Past Perfect",
    "explanation": "The Past Perfect tense (had + V3) places an action further back in time than the Past Simple. It clarifies the sequence of events in the past (e.g., 'I had eaten before he arrived').",
    "difficulty": "Intermediate"
  },
  {
    "id": 69,
    "question": "Which conjunction pair is used to connect two alternatives of equal grammatical weight?",
    "options": [
      "Either... or",
      "Neither... nor",
      "Both... and",
      "Not only... but also"
    ],
    "answer": "Either... or",
    "explanation": "'Either... or' presents a choice between two distinct possibilities. 'Both... and' adds elements, while 'Neither... nor' negates both. These are known as correlative conjunctions.",
    "difficulty": "Intermediate"
  },
  {
    "id": 70,
    "question": "What distinguishes a 'finite verb' from a 'non-finite verb'?",
    "options": [
      "Finite verbs show tense; non-finite verbs do not",
      "Non-finite verbs must always start the sentence",
      "Finite verbs cannot be the main verb",
      "Non-finite verbs require a subject"
    ],
    "answer": "Finite verbs show tense; non-finite verbs do not",
    "explanation": "A finite verb is a verb that functions as the main verb of a sentence and shows tense, person, and number (e.g., 'he runs'). Non-finite verbs (infinitives, gerunds, participles) do not show tense.",
    "difficulty": "Intermediate"
  },
  {
    "id": 71,
    "question": "Which sentence correctly employs the 'Inverted Conditional' structure for a hypothetical past event?",
    "options": [
      "Had I known about the delay, I would have taken a different route.",
      "If I had known about the delay, I would have taken a different route.",
      "I would have taken a different route, had I known about the delay.",
      "Were I to know about the delay, I would take a different route."
    ],
    "answer": "Had I known about the delay, I would have taken a different route.",
    "explanation": "The inverted conditional omits 'if' by placing the auxiliary 'Had' before the subject. While option C is also grammatically correct, option A demonstrates the specific fronted inversion structure requested as the primary transformation.",
    "difficulty": "Advanced"
  },
  {
    "id": 72,
    "question": "In the sentence 'She is the only one of the employees who [has/have] been here longer than me,' which verb form is grammatically correct and why?",
    "options": [
      "has, because 'one' is the singular antecedent focused on by the restrictive phrase",
      "have, because 'employees' is the plural noun nearest to the relative pronoun",
      "has, because the relative pronoun 'who' requires a singular verb in all cases",
      "have, because the subject 'She' is pluralized by the context of the group"
    ],
    "answer": "has, because 'one' is the singular antecedent focused on by the restrictive phrase",
    "explanation": "The intervening prepositional phrase 'of the employees' does not make the antecedent plural. The clause modifies 'the only one,' requiring the singular verb 'has.'",
    "difficulty": "Advanced"
  },
  {
    "id": 73,
    "question": "What distinguishes a 'Pseudocleft' sentence from a standard 'It-cleft' sentence?",
    "options": [
      "A pseudocleft begins with a wh-clause (What I need is...) rather than the dummy pronoun 'It'",
      "A pseudocleft places the emphasized element at the beginning of the sentence",
      "A pseudocleft is used exclusively for questions, whereas an it-cleft is for statements",
      "A pseudocleft cannot be used to focus on a noun phrase, only a verb phrase"
    ],
    "answer": "A pseudocleft begins with a wh-clause (What I need is...) rather than the dummy pronoun 'It'",
    "explanation": "Pseudoclefts (e.g., 'What I need is a coffee') utilize a nominal relative clause as the subject, whereas it-clefts (e.g., 'It is a coffee that I need') use the dummy 'It' + be + focus.",
    "difficulty": "Advanced"
  },
  {
    "id": 74,
    "question": "When using the verb 'proposition,' which preposition is required to connect it to an infinitive verb indicating the intended action?",
    "options": [
      "The verb 'proposition' is strictly transitive and never takes a preposition before an infinitive",
      "to",
      "with",
      "for"
    ],
    "answer": "The verb 'proposition' is strictly transitive and never takes a preposition before an infinitive",
    "explanation": "Unlike 'propositional' logic, the verb meaning 'to suggest' or 'to solicit sex' is transitive (e.g., 'He propositioned her'). It does not take a prepositional link to an infinitive like 'proposed to do.'",
    "difficulty": "Advanced"
  },
  {
    "id": 75,
    "question": "Which sentence demonstrates a 'Cataphoric' reference?",
    "options": [
      "Although she was tired, Mary continued working.",
      "Mary continued working because she was tired.",
      "Working hard is required if you want to succeed.",
      "The book which I mentioned was on the table."
    ],
    "answer": "Although she was tired, Mary continued working.",
    "explanation": "Cataphora occurs when a pronoun ('she') refers forward to a noun phrase ('Mary') that appears later in the sentence.",
    "difficulty": "Advanced"
  },
  {
    "id": 76,
    "question": "What is the grammatical term for the construction 'Whom do you want to see?' compared to 'Who do you want to see?'?",
    "options": [
      "The first is 'Hypercorrection'; the second is the standard colloquial form",
      "The first is 'Preposition Stranding'; the second is 'Pied-Piping'",
      "The first is 'Subject Case'; the second is 'Object Case'",
      "The first is 'Fronting'; the second is 'Inversion'"
    ],
    "answer": "The first is 'Hypercorrection'; the second is the standard colloquial form",
    "explanation": "In colloquial English, 'who' replaces 'whom' as the object pronoun. Using 'whom' here is technically grammatically precise in formal register, but often labeled hypercorrection when used awkwardly, though technically 'whom' is the correct object form. However, the best fit for the *distinction* in technical grammar regarding the shift is that the first maintains the formal objective case rule.",
    "difficulty": "Advanced"
  },
  {
    "id": 77,
    "question": "In the context of aspect, what is the difference between 'I am writing' and 'I write'?",
    "options": [
      "'I am writing' is progressive aspect (ongoing), while 'I write' is simple aspect (habitual or factual)",
      "'I am writing' is present tense, while 'I write' is future tense",
      "'I am writing' implies a completed action, while 'I write' implies an incomplete action",
      "'I am writing' is subjunctive, while 'I write' is indicative"
    ],
    "answer": "'I am writing' is progressive aspect (ongoing), while 'I write' is simple aspect (habitual or factual)",
    "explanation": "The progressive aspect (be + -ing) denotes an action in progress. The simple aspect denotes a timeless fact, a habitual action, or a completed event.",
    "difficulty": "Advanced"
  },
  {
    "id": 78,
    "question": "Which modifier creates a 'Flat Adverb'?",
    "options": [
      "Using an adjective form to modify a verb (e.g., 'Drive safe')",
      "Using an adverb ending in -ly (e.g., 'Drive safely')",
      "Using a noun to modify a verb (e.g., 'Drive home')",
      "Using a prepositional phrase as an adverb (e.g., 'Drive with care')"
    ],
    "answer": "Using an adjective form to modify a verb (e.g., 'Drive safe')",
    "explanation": "Flat adverbs are adjectives that function as adverbs without the -ly suffix (e.g., 'drive safe,' 'take it easy'), common in casual English but often criticized in formal writing.",
    "difficulty": "Advanced"
  },
  {
    "id": 79,
    "question": "Identify the 'Extraposed Object' in the following sentence: 'I find it strange that he left.'",
    "options": [
      "that he left",
      "it",
      "strange",
      "I"
    ],
    "answer": "that he left",
    "explanation": "The extraposed object is the subordinate clause ('that he left') that has been moved to the end of the sentence. The dummy 'it' occupies the object position to satisfy the grammatical requirement of the verb.",
    "difficulty": "Advanced"
  },
  {
    "id": 80,
    "question": "In the sentence 'The horse raced past the barn fell,' why is this structurally ambiguous without commas?",
    "options": [
      "It is a 'Garden Path' sentence where 'raced' is interpreted as a past tense verb, but functions as a reduced relative clause",
      "It is a 'Dangling Participle' because the modifier is not placed next to the noun",
      "It contains a 'Lexical Ambiguity' where 'raced' can be a noun or a verb",
      "It is a 'Run-on Sentence' lacking a coordinating conjunction"
    ],
    "answer": "It is a 'Garden Path' sentence where 'raced' is interpreted as a past tense verb, but functions as a reduced relative clause",
    "explanation": "Readers initially parse 'raced' as the main verb. The sentence forces a re-analysis when 'fell' is reached, revealing 'raced past the barn' is actually a reduced relative clause ('The horse [that was] raced past the barn fell').",
    "difficulty": "Advanced"
  },
  {
    "id": 81,
    "question": "What is the specific function of the 'dummy operator' 'do' in the question 'Do you like coffee?'?",
    "options": [
      "It carries the tense and agreement for the main verb, which lacks inflection",
      "It acts as an auxiliary to indicate emphasis",
      "It replaces the main verb to avoid repetition",
      "It functions as a catenative verb connecting the subject to the object"
    ],
    "answer": "It carries the tense and agreement for the main verb, which lacks inflection",
    "explanation": "In English interrogatives, 'do' appears because the main verb 'like' is lexical (non-auxiliary) and cannot invert with the subject. 'Do' supports the tense.",
    "difficulty": "Advanced"
  },
  {
    "id": 82,
    "question": "Which sentence correctly uses the subjunctive mood to express a demand in a formal context?",
    "options": [
      "I require that he be present at the meeting.",
      "I require that he is present at the meeting.",
      "I require that he should be present at the meeting.",
      "I require that he will be present at the meeting."
    ],
    "answer": "I require that he be present at the meeting.",
    "explanation": "The mandative subjunctive uses the base form of the verb ('be') regardless of the subject. It is triggered by verbs of urgency or demand (require, insist, suggest).",
    "difficulty": "Advanced"
  },
  {
    "id": 83,
    "question": "In the sentence 'He is [to blame / to blame for the accident],' is 'to blame' an infinitive of purpose or an adjective?",
    "options": [
      "Adjective; the phrase functions as a subject complement meaning 'responsible'",
      "Infinitive of purpose; it indicates he needs to assign blame",
      "Passive infinitive; the object 'the accident' is omitted",
      "Catena; it is part of a continuous verb structure"
    ],
    "answer": "Adjective; the phrase functions as a subject complement meaning 'responsible'",
    "explanation": "'To blame' acts as an adjective (similar to 'to blame for') meaning 'at fault.' Historically, it was a passive infinitive ('to be blamed'), but the 'be' has been dropped.",
    "difficulty": "Advanced"
  },
  {
    "id": 84,
    "question": "What is the 'Pro-form' used to replace an entire clause, as seen in: 'He said he was busy, and I believe [it].'?",
    "options": [
      "It",
      "So",
      "That",
      "One"
    ],
    "answer": "So",
    "explanation": "While 'it' is sometimes used in casual speech, 'so' is the distinct grammatical pro-form for clausal substitution (e.g., 'I hope so').",
    "difficulty": "Advanced"
  },
  {
    "id": 85,
    "question": "Which logical connector indicates a relationship of 'addition' combined with 'scalar emphasis'?",
    "options": [
      "Furthermore",
      "Moreover",
      "And",
      "But"
    ],
    "answer": "Moreover",
    "explanation": "Both 'furthermore' and 'moreover' indicate addition, but 'moreover' implies that the new point is more significant or convincing than the previous one (scalar emphasis).",
    "difficulty": "Advanced"
  },
  {
    "id": 86,
    "question": "In the phrase 'A five-year-old boy,' why is 'year' singular?",
    "options": [
      "Nouns modifying other nouns (attributive nouns) are almost always singular",
      "The number 'five' is a plural marker, making the noun redundant",
      "It is a compound adjective requiring a singular head",
      "It is an exception to the rule of hyphenation"
    ],
    "answer": "Nouns modifying other nouns (attributive nouns) are almost always singular",
    "explanation": "When a noun modifies another noun (attributive position), it takes the singular form. We say 'shoe store' not 'shoes store.'",
    "difficulty": "Advanced"
  },
  {
    "id": 87,
    "question": "What is the term for a verb that can take two objects, such as 'give' in 'She gave him a book'?",
    "options": [
      "Ditransitive",
      "Transitive",
      "Bitransitive",
      "Complex-transitive"
    ],
    "answer": "Ditransitive",
    "explanation": "Ditransitive verbs take two objects: an indirect object (him) and a direct object (a book).",
    "difficulty": "Advanced"
  },
  {
    "id": 88,
    "question": "Which sentence contains a 'Resultative' adjective?",
    "options": [
      "The river froze solid.",
      "The frozen river was cold.",
      "The freezing water hurt my hands.",
      "He froze the water."
    ],
    "answer": "The river froze solid.",
    "explanation": "In 'The river froze solid,' the adjective 'solid' describes the result of the freezing action. This is a resultative secondary predicate.",
    "difficulty": "Advanced"
  },
  {
    "id": 89,
    "question": "What is the difference in meaning between 'The judge was strict' and 'The judge was severe'?",
    "options": [
      "'Strict' implies adherence to rules; 'severe' implies harshness or a lack of leniency that may be cruel",
      "'Strict' is a legal term; 'severe' is a medical term",
      "'Strict' implies rigidity; 'severe' implies flexibility",
      "There is no difference; they are synonymous"
    ],
    "answer": "'Strict' implies adherence to rules; 'severe' implies harshness or a lack of leniency that may be cruel",
    "explanation": "Nuance distinguishes these terms. 'Strict' suggests rigorous enforcement of standards, while 'severe' suggests an extreme, often punitive degree of harshness.",
    "difficulty": "Advanced"
  },
  {
    "id": 90,
    "question": "In a sentence containing 'Neither... nor...', which verb form is correct when the subjects differ in number (e.g., 'Neither the father nor the sons ___')?",
    "options": [
      "The verb agrees with the nearest subject (Proximity Rule)",
      "The verb is always singular",
      "The verb is always plural",
      "The verb agrees with the first subject mentioned"
    ],
    "answer": "The verb agrees with the nearest subject (Proximity Rule)",
    "explanation": "With 'neither/nor' and 'either/or', the verb generally agrees with the subject closest to it (the principle of proximity).",
    "difficulty": "Advanced"
  },
  {
    "id": 91,
    "question": "What is the 'Recency Effect' in the context of serial position and end-weight in syntax?",
    "options": [
      "Readers retain information better when it is placed at the end of a sentence (End Focus)",
      "Readers prefer older information at the start of the sentence",
      "Writers should place the most important information in the middle",
      "The main verb should always be the last word"
    ],
    "answer": "Readers retain information better when it is placed at the end of a sentence (End Focus)",
    "explanation": "End Focus is a principle of English syntax where new or important information is placed at the end of the clause to maximize impact (recency).",
    "difficulty": "Advanced"
  },
  {
    "id": 92,
    "question": "Which sentence uses a 'Dangling Modifier'?",
    "options": [
      "Walking down the street, the trees were beautiful.",
      "Walking down the street, I saw the beautiful trees.",
      "Having walked down the street, the trees were beautiful.",
      "To walk down the street, the trees were needed."
    ],
    "answer": "Walking down the street, the trees were beautiful.",
    "explanation": "The implied subject of the participial phrase 'Walking down the street' must be the subject of the main clause. Here, 'trees' cannot walk, making it a dangling modifier.",
    "difficulty": "Advanced"
  },
  {
    "id": 93,
    "question": "In the context of 'modal periphrasis,' what is the function of 'be to' in 'The President is to visit China'?",
    "options": [
      "It indicates a formal arrangement or destiny",
      "It indicates an obligation or command",
      "It indicates a possibility",
      "It indicates a condition"
    ],
    "answer": "It indicates a formal arrangement or destiny",
    "explanation": "The 'be to' construction (semi-modal) often signifies a formal plan, arrangement, or destiny, distinct from the obligation of 'must' or the future of 'will.'",
    "difficulty": "Advanced"
  },
  {
    "id": 94,
    "question": "Identify the 'Zero Relative Pronoun' in: 'The man ___ I saw.'",
    "options": [
      "[null]",
      "who",
      "whom",
      "that"
    ],
    "answer": "[null]",
    "explanation": "In a restrictive relative clause where the relative pronoun is the object, English allows the pronoun to be omitted (the zero relative pronoun).",
    "difficulty": "Advanced"
  },
  {
    "id": 95,
    "question": "What is the definition of a 'light verb'?",
    "options": [
      "A verb that has little semantic meaning of its own and contributes mainly to grammatical structure (e.g., 'take' in 'take a walk')",
      "A verb that is conjugated irregularly",
      "A verb that indicates speed or lack of weight",
      "A verb that functions as an auxiliary without a main verb"
    ],
    "answer": "A verb that has little semantic meaning of its own and contributes mainly to grammatical structure (e.g., 'take' in 'take a walk')",
    "explanation": "Light verbs (like 'take,' 'make,' 'do,' 'give') carry tense/aspect but rely on the noun (complement) for the core meaning (delexicalization).",
    "difficulty": "Advanced"
  },
  {
    "id": 96,
    "question": "Which distinction defines the difference between 'historic' and 'historical'?",
    "options": [
      "'Historic' means important in history; 'historical' means relating to history in general",
      "'Historic' refers to the past; 'historical' refers to the future",
      "'Historic' is an adjective; 'historical' is an adverb",
      "'Historic' is British English; 'historical' is American English"
    ],
    "answer": "'Historic' means important in history; 'historical' means relating to history in general",
    "explanation": "A 'historic' event is momentous. A 'historical' novel or figure is simply from the past or pertains to the study of the past.",
    "difficulty": "Advanced"
  },
  {
    "id": 97,
    "question": "What is the 'Double Genitive' construction in the phrase: 'A friend of mine'?",
    "options": [
      "A post-genitive construction where the possessor is represented by an independent possessive pronoun",
      "A double negative used in dialect",
      "A redundancy error that should be corrected to 'A friend of me'",
      "A specific Germanic grammatical case marking"
    ],
    "answer": "A post-genitive construction where the possessor is represented by an independent possessive pronoun",
    "explanation": "The double genitive ('of' + possessive pronoun) allows definiteness and indefiniteness simultaneously (e.g., 'A friend of John's' implies John has multiple friends).",
    "difficulty": "Advanced"
  },
  {
    "id": 98,
    "question": "In the sentence 'I sent him the letter,' what is the structural change to convert it to the 'Dative Shift' passive?",
    "options": [
      "He was sent the letter.",
      "The letter was sent him.",
      "The letter was sent to him.",
      "Him was sent the letter."
    ],
    "answer": "He was sent the letter.",
    "explanation": "The dative shift passivization promotes the indirect object (him) to the subject position, retaining the double object construction pattern.",
    "difficulty": "Advanced"
  },
  {
    "id": 99,
    "question": "Which feature characterizes 'Non-Restrictive' relative clauses?",
    "options": [
      "They are set off by commas and provide extra, non-essential information",
      "They are not set off by commas and define the noun",
      "They always use 'that' as the relative pronoun",
      "They modify an entire sentence rather than a noun"
    ],
    "answer": "They are set off by commas and provide extra, non-essential information",
    "explanation": "Non-restrictive (appositive) clauses add parenthetical information. If removed, the sentence remains grammatically complete and identifiable.",
    "difficulty": "Advanced"
  },
  {
    "id": 100,
    "question": "What is the difference between 'continual' and 'continuous'?",
    "options": [
      "'Continual' implies recurring breaks; 'continuous' means unbroken",
      "'Continual' means unbroken; 'continuous' implies recurring breaks",
      "'Continual' is used for spatial distance; 'continuous' is for time",
      "They are completely synonymous in all contexts"
    ],
    "answer": "'Continual' implies recurring breaks; 'continuous' means unbroken",
    "explanation": "A 'continual' annoyance happens repeatedly (e.g., knocks at the door). A 'continuous' flow has no interruptions (e.g., a stream).",
    "difficulty": "Advanced"
  }
]